hek_voevent_tools/__init__.py
hek_voevent_tools/config.ini
hek_voevent_tools/config.py
hek_voevent_tools/create_event.py
hek_voevent_tools/export_event.py
hek_voevent_tools/ingest_csv.py
hek_voevent_tools/voevent.py
hek_voevent_tools-1.0.3.dist-info/METADATA
hek_voevent_tools-1.0.3.dist-info/WHEEL
hek_voevent_tools-1.0.3.dist-info/top_level.txt
hek_voevent_tools-1.0.3.dist-info/RECORD
