Metadata-Version: 2.4
Name: hek-voevent-tools
Version: 1.0.3
Summary: Generate VOEvent XMLs
Author: Justin Cheng
License: MIT
Keywords: voevent,pandas,xml,HEK,HEKSearch
Requires-Python: >=3.10
Requires-Dist: pandas>=2.0
Requires-Dist: requests>=2.0
